kpay_spider_utils/__init__.py
kpay_spider_utils/cycle_spider_func.py
kpay_spider_utils/func.py
kpay_spider_utils/lark_api.py
kpay_spider_utils/lark_bot.py
kpay_spider_utils-1.6.dist-info/METADATA
kpay_spider_utils-1.6.dist-info/WHEEL
kpay_spider_utils-1.6.dist-info/top_level.txt
kpay_spider_utils-1.6.dist-info/RECORD
