Metadata-Version: 2.1
Name: kpay-spider-utils
Version: 1.6
Summary: 增加cycle_spider.func
Home-page: https://github.com/yourusername/my_project
Author: 车小炮
Author-email: denghui.che@kpay-group.com
Classifier: Programming Language :: Python :: 3
Classifier: License :: OSI Approved :: MIT License
Classifier: Operating System :: OS Independent
